easysetuppy/__init__.py
easysetuppy/classifiers.py
easysetuppy-1.1.9.dist-info/METADATA
easysetuppy-1.1.9.dist-info/RECORD
easysetuppy-1.1.9.dist-info/WHEEL
easysetuppy-1.1.9.dist-info/entry_points.txt
easysetuppy-1.1.9.dist-info/top_level.txt
